apputils/discovery/__init__.py
apputils/discovery/arguments.py
apputils/discovery/commands.py
apputils_discovery-2.0.2.dist-info/LICENSE
apputils_discovery-2.0.2.dist-info/METADATA
apputils_discovery-2.0.2.dist-info/WHEEL
apputils_discovery-2.0.2.dist-info/top_level.txt
apputils_discovery-2.0.2.dist-info/zip-safe
apputils_discovery-2.0.2.dist-info/RECORD
