Metadata-Version: 2.1
Name: apputils-discovery
Version: 2.0.2
Summary: AppUtils discovery package
Home-page: UNKNOWN
Author: hapylestat@apache.org
License: ASF
Platform: UNKNOWN
Classifier: Programming Language :: Python
Classifier: Programming Language :: Python :: 3
Classifier: Programming Language :: Python :: 3.8
Requires-Python: >=3.8
Requires-Dist: apputils (==2.0.2)
